<?xml version="1.0" encoding="UTF-8"?>
<!-- level1 actor details-->
<!--  -->
<data>
	<weaponLimit>10</weaponLimit>
	<actor>
		<id>1</id>
		<name>foundation_stone_left</name>
		<xcord>0</xcord>
		<ycord>0</ycord>
		<material>foundation</material>
		<flammable>0</flammable>
		<crushable>0</crushable>
	</actor>
	<actor>
		<id>2</id>
		<name>foundation_stone_middle</name>
		<xcord>74</xcord>
		<ycord>0</ycord>
		<material>stone</material>
		<flammable>0</flammable>
		<crushable>0</crushable>
	</actor>
	<actor>
		<id>3</id>
		<name>foundation_stone_middle</name>
		<xcord>125</xcord>
		<ycord>0</ycord>
		<material>foundation</material>
		<flammable>0</flammable>
		<crushable>0</crushable>
	</actor>
	<actor>
		<id>3</id>
		<name>foundation_stone_middle</name>
		<xcord>175</xcord>
		<ycord>0</ycord>
		<material>foundation</material>
		<flammable>0</flammable>
		<crushable>0</crushable>
	</actor>
	<actor>
		<id>3</id>
		<name>roof_stone_left</name>
		<xcord>-15</xcord>
		<ycord>200</ycord>
		<material>foundation</material>
		<flammable>0</flammable>
		<crushable>0</crushable>
	</actor>
	<actor>
		<id>3</id>
		<name>roof_golden_middle</name>
		<xcord>125</xcord>
		<ycord>220</ycord>
		<material>gold</material>
		<flammable>0</flammable>
		<crushable>0</crushable>
	</actor>
<!-- 	<actor> -->
<!-- 		<id>3</id> -->
<!-- 		<name>stone_block_big</name> -->
<!-- 		<xcord>125</xcord> -->
<!-- 		<ycord>220</ycord> -->
<!-- 		<material>foundation</material> -->
<!-- 		<flammable>0</flammable> -->
<!-- 		<crushable>0</crushable> -->
<!-- 	</actor> -->
	<actor>
		<id>3</id>
		<name>roof_stone_right</name>
		<xcord>270</xcord>
		<ycord>200</ycord>
		<material>foundation</material>
		<flammable>0</flammable>
		<crushable>0</crushable>
	</actor>
	<actor>
		<id>4</id>
		<name>foundation_stone_right</name>
		<xcord>245</xcord>
		<ycord>0</ycord>
		<material>stone</material>
		<flammable>0</flammable>
		<crushable>0</crushable>
	</actor>
	<actor>
		<id>5</id>
		<name>pillar5</name>
		<xcord>-10</xcord>
		<ycord>69</ycord>
		<material>stone</material>
		<flammable>0</flammable>
		<crushable>0</crushable>
	</actor>
	<actor>
		<id>7</id>
		<name>pillar5</name>
		<xcord>260</xcord>
		<ycord>69</ycord>
		<material>gold</material>
		<flammable>0</flammable>
		<crushable>0</crushable>
	</actor>
	<actor>
		<id>7</id>
		<name>pillar5</name>
		<xcord>125</xcord>
		<ycord>80</ycord>
		<material>stone</material>
		<flammable>0</flammable>
		<crushable>0</crushable>
	</actor>
	<actor>
		<id>8</id>
		<name>box_golden</name>
		<xcord>198</xcord>
		<ycord>80</ycord>
		<material>gold</material>
		<flammable>0</flammable>
		<crushable>0</crushable>
	</actor>
	<actor>
		<id>8</id>
		<name>box_golden</name>
		<xcord>198</xcord>
		<ycord>124</ycord>
		<material>gold</material>
		<flammable>0</flammable>
		<crushable>0</crushable>
	</actor>
	<actor>
		<id>8</id>
		<name>roof_stone_middle</name>
		<xcord>130</xcord>
		<ycord>200</ycord>
		<material>stone</material>
		<flammable>0</flammable>
		<crushable>0</crushable>
	</actor>
	<actor>
		<id>8</id>
		<name>slab_stone_very_long</name>
		<xcord>25</xcord>
		<ycord>220</ycord>
		<material>gold</material>
		<flammable>0</flammable>
		<crushable>0</crushable>
	</actor>
	<actor>
		<id>8</id>
		<name>slab_stone_very_long</name>
		<xcord>230</xcord>
		<ycord>220</ycord>
		<material>gold</material>
		<flammable>0</flammable>
		<crushable>0</crushable>
	</actor>
	<actor>
		<id>8</id>
		<name>nandu</name>
		<xcord>50</xcord>
		<ycord>80</ycord>
		<material>gold</material>
		<flammable>0</flammable>
		<crushable>1</crushable>
	</actor>
	<actor>
		<id>8</id>
		<name>prakash</name>
		<xcord>180</xcord>
		<ycord>80</ycord>
		<material>gold</material>
		<flammable>0</flammable>
		<crushable>1</crushable>
	</actor>
</data>